{"0": ["mixed5b-148", "mixed5b-70"], "1": ["mixed5b-494", "mixed5b-520", "mixed5b-730"], "2": ["mixed5b-659", "mixed5b-477", "mixed5b-600", "mixed5b-408", "mixed5b-677", "mixed5b-543", "mixed5b-444", "mixed5b-612", "mixed5b-706", "mixed5b-438", "mixed5b-464", "mixed5b-763", "mixed5b-424", "mixed5b-579", "mixed5b-655", "mixed5b-512", "mixed5b-587", "mixed5b-495", "mixed5b-667", "mixed5b-716", "mixed5b-428", "mixed5b-630", "mixed5b-561", "mixed5b-507", "mixed5b-536", "mixed5b-417", "mixed5b-616"], "3": ["mixed5b-781", "mixed5b-795", "mixed5b-772", "mixed5b-888"], "4": ["mixed5b-197", "mixed5b-259"]}