{"0": ["91", "126"], "1": ["79", "103"], "2": ["35", "142"], "3": ["26", "124"], "4": ["43", "117", "154"], "5": ["2", "159"], "6": ["25", "55"], "7": ["52", "78", "53"], "8": ["41", "86"], "9": ["22", "107"], "10": ["20", "111", "152", "7", "60", "80"], "11": ["57", "83", "158", "40", "134"], "12": ["63", "99"], "13": ["29", "151"], "14": ["0", "46", "50", "58", "74", "39", "92", "66", "132", "33", "37", "64", "98", "139", "155", "149", "54", "146", "65", "105", "129"], "15": ["12", "72", "122", "136", "95", "96", "16", "135", "110", "137", "148"], "16": ["138", "36", "3", "85", "143", "144", "5", "88", "130"]}