{"0": ["mixed5a_3x3-59", "mixed5a_3x3-69"], "1": ["mixed5a_3x3-105", "mixed5a_3x3-95"], "2": ["mixed5a_3x3-129", "mixed5a_3x3-18"], "3": ["mixed5a_3x3-103", "mixed5a_3x3-143", "mixed5a_3x3-74"], "4": ["mixed5a_3x3-110", "mixed5a_3x3-50"], "5": ["mixed5a_3x3-114", "mixed5a_3x3-19"], "6": ["mixed5a_3x3-126", "mixed5a_3x3-77"], "7": ["mixed5a_3x3-135", "mixed5a_3x3-138"], "8": ["mixed5a_3x3-130", "mixed5a_3x3-38"], "9": ["mixed5a_3x3-147", "mixed5a_3x3-13", "mixed5a_3x3-43"], "10": ["mixed5a_3x3-136", "mixed5a_3x3-37"], "11": ["mixed5a_3x3-48", "mixed5a_3x3-73"], "12": ["mixed5a_3x3-29", "mixed5a_3x3-5"], "13": ["mixed5a_3x3-134", "mixed5a_3x3-86", "mixed5a_3x3-65", "mixed5a_3x3-68"], "14": ["mixed5a_3x3-63", "mixed5a_3x3-122", "mixed5a_3x3-140", "mixed5a_3x3-7", "mixed5a_3x3-75", "mixed5a_3x3-10", "mixed5a_3x3-28"], "15": ["mixed5a_3x3-108", "mixed5a_3x3-92"], "16": ["mixed5a_3x3-109", "mixed5a_3x3-125"], "17": ["mixed5a_3x3-139", "mixed5a_3x3-21"]}