{"0": ["mixed5a-96", "mixed5a-99"], "1": ["mixed5a-116", "mixed5a-70", "mixed5a-175", "mixed5a-0", "mixed5a-210", "mixed5a-140", "mixed5a-47"], "2": ["mixed5a-18", "mixed5a-190", "mixed5a-222", "mixed5a-121", "mixed5a-255", "mixed5a-221", "mixed5a-158", "mixed5a-232", "mixed5a-1", "mixed5a-122", "mixed5a-78"], "3": ["mixed5a-604", "mixed5a-650"], "4": ["mixed5a-485", "mixed5a-435", "mixed5a-364"], "5": ["mixed5a-718", "mixed5a-713", "mixed5a-714", "mixed5a-762", "mixed5a-811", "mixed5a-739", "mixed5a-734", "mixed5a-757", "mixed5a-784"]}